Metadata-Version: 2.1
Name: modbus-tcprtu
Version: 1.0.0
Summary: A ModbusRTU Over TCP/IP library, depends on modbus_tk.
Home-page: https://github.com/sintrb/modbus_tcprtu/
Author: trb
Author-email: sintrb@gmail.com
License: UNKNOWN
Keywords: modbus,modbus_tk,modbus_tcp,modbus_rtu
Platform: UNKNOWN
